caparg/__init__.py
caparg/_api.py
caparg/_version.py
caparg/test/__init__.py
caparg/test/__main__.py
caparg/test/helper_subcommands.py
caparg/test/test_subcommands.py
caparg-19.11.0.dist-info/METADATA
caparg-19.11.0.dist-info/WHEEL
caparg-19.11.0.dist-info/top_level.txt
caparg-19.11.0.dist-info/RECORD
