Metadata-Version: 2.1
Name: caparg
Version: 19.11.0
Summary: Captain Arguments: Ready for subcommand
Home-page: UNKNOWN
Author: Moshe Zadka
Author-email: zadka.moshe@gmail.com
License: MIT
Platform: UNKNOWN
Requires-Dist: attrs
Requires-Dist: incremental
Requires-Dist: pyrsistent
Requires-Dist: typing ; python_version == "2.7"
